Metadata-Version: 2.1
Name: FingerReader
Version: 1.0.0
Summary: Python library for fingerprint sensors.
Home-page: UNKNOWN
Author: Aryan Arabshahi
Author-email: aryan.arabshahi.programmer@gmail.com
License: UNKNOWN
Keywords: fingerprint,FingerReader
Platform: UNKNOWN
Requires-Python: >=3.6
